{
  "date": "2025-06-19",
  "status": "ok",
  "n_events": 351748,
  "total_pnl": 8.33500000000285,
  "sharpe": 0.7441540355344931,
  "max_drawdown": -13.599999999999739,
  "total_fills": 9925,
  "fill_rate": 0.3039443865988853,
  "avg_spread_bps": 7.483227626151792,
  "avg_abs_inventory": 14.346219442865264,
  "max_abs_inventory": 100.0,
  "total_fees": 0.0,
  "n_short_gaps": 2483,
  "n_long_gaps": 0,
  "n_gap_closures": 0,
  "gap_closure_pnl": 0,
  "mm_only_pnl": 8.33500000000285,
  "n_hysteresis_skips": 79744,
  "hysteresis_skip_rate": 0.8300527734696215,
  "avg_markout_bps": 0.06508236531313016,
  "pct_adverse_fills": 0.36614609571788415,
  "n_markouts": 9925
}