{
  "date": "2025-07-05",
  "status": "ok",
  "n_events": 253502,
  "total_pnl": 20.86500000000001,
  "sharpe": 1.7221068638115438,
  "max_drawdown": -14.025000000000603,
  "total_fills": 4469,
  "fill_rate": 0.22320447507741484,
  "avg_spread_bps": 7.507553676887738,
  "avg_abs_inventory": 28.333990536277604,
  "max_abs_inventory": 100.0,
  "total_fees": 0.0,
  "n_short_gaps": 3825,
  "n_long_gaps": 0,
  "n_gap_closures": 0,
  "gap_closure_pnl": 0,
  "mm_only_pnl": 20.86500000000001,
  "n_hysteresis_skips": 55249,
  "hysteresis_skip_rate": 0.8465982224946368,
  "avg_markout_bps": 0.7089581052482181,
  "pct_adverse_fills": 0.28507496084135153,
  "n_markouts": 4469
}