{
  "date": "2025-06-27",
  "status": "ok",
  "n_events": 408826,
  "total_pnl": -8.214999999999108,
  "sharpe": -4.896864909917194,
  "max_drawdown": -8.474999999999142,
  "total_fills": 1490,
  "fill_rate": 0.11230027132951462,
  "avg_spread_bps": 9.829219472821135,
  "avg_abs_inventory": 1.4025434091464906,
  "max_abs_inventory": 35.0,
  "total_fees": 0.0,
  "n_short_gaps": 1649,
  "n_long_gaps": 0,
  "n_gap_closures": 0,
  "gap_closure_pnl": 0,
  "mm_only_pnl": -8.214999999999108,
  "n_hysteresis_skips": 97592,
  "hysteresis_skip_rate": 0.9363498551225222,
  "avg_markout_bps": -1.6284188480847517,
  "pct_adverse_fills": 0.674496644295302,
  "n_markouts": 1490
}